EZobject2xml/__init__.py
EZobject2xml/xmltoolMod.py
EZobject2xml-1.0.2.dist-info/LICENCE
EZobject2xml-1.0.2.dist-info/METADATA
EZobject2xml-1.0.2.dist-info/WHEEL
EZobject2xml-1.0.2.dist-info/top_level.txt
EZobject2xml-1.0.2.dist-info/RECORD
