Metadata-Version: 2.1
Name: EZobject2xml
Version: 1.0.2
Summary: Easily save and load any object data to/from a xml file
Home-page: https://github.com/JoshuaWar/EZobject2xml
Author: Alexandre CHAPELLE
Author-email: alexandre.chapelle@yahoo.fr
License: UNKNOWN
Platform: UNKNOWN
Classifier: Programming Language :: Python :: 3
Classifier: License :: OSI Approved :: MIT License
Classifier: Operating System :: OS Independent
Requires-Python: >=3.8
